{
  "files.banner.free_space_is_available": "Not much free storage space",
  "files.banner.not_enough_space": "There is not enough free space in the file system available",
  "files.banner.complete_download": "Файлы загружены",
  "files.action.delete_file": "Delete",
  "files.action.select_all": "Select all",
  "files.folders.records": "Records",
  "files.folders.tests_and_voting": "Tests and voting",
  "files.folders.converted_records": "Converted records",
  "people.action_contact.open.delete": "Delete",
  "people.action_target_contact.open.edit": "Edit",
  "people.import_contact_info.snackbar.template": "Imported contacts: %s",
  "people.create_contact.modal_content.save": "Save",
  "people.create_contact.modal_content.import": "Import",
  "test.duration.fifteen_minutes": "15 minutes",
  "branding.newsletter.html_template_text_for_notification": "Use your own HTML-template for a reminder letter ",
  "branding.newsletter.use_outer_smtp_server": "Use an external SMTP server",
  "branding.logo.menu_service": "Menu",
  "branding.logo.landing_and_notes": "Landings and records",
  "event.landing.switch.language_RU": "РУС",
  "event.landing.switch.language_ENG": "ENG",
  "event_edit.edit_reminders.time_one_day_before": "A day before",
  "event_edit.edit_reminders.time_fifteen_min_before": "15 minutes before",
  "event_edit.edit_reminders.time_hour_before": "One hour before",
  "event_edit.edit_reminders.time_week_before": "One week before ",
  "event_edit.edit_reminders.time_mailing_after": "Mailout after",
  "event_edit.edit_reminders.time_set_own_date": "Set my date",
  "event_end.email_to_participants.paid_participants": "Paid",
  "email_page.inbox.subject_invite_template": "You are invited to a webinar \"%s\"",
  "email_page.inbox.subject_reminder_template": "Webinar reminder",
  "email_page.inbox.subject_reminder_template_format": "Webinar \"%s\" reminder",
  "email_page.inbox.subject_question_template_format": "Question about your event",
  "email_page.inbox.subject_answer_template_format": "The answer to your question is ready",
  "email_page.inbox.invitation_to_organization": "You have been invited to the organization",
  "email_page.inbox.success_webinar_payment": "Webinar payment successful",
  "email_page.inbox.success_registration_to_webinar": "Register for the webinar \"%s\"",
  "email_page.inbox.webinar_registration": "Register for the webinar \"%s\"",
  "email_page.inbox.participation_agreed": "Participation in the webinar is approved",
  "organization.employee_status.invited": "Invited",
  "header_nav_form.notification_menu.invited_to_organization": "Invitation to the organization",
  "tariffs_page.main_content.participants": "Participants",
  "tariffs_page.main_content.speakers": "Speakers",
  "tariffs_page.main_content.hours_months": "Hours/month",
  "tariffs_page.main_content.buy": "Buy",
  "tariffs_page.tariff_period.periods_dropdown_month": "Month",
  "tariffs_page.add_option.speaker": "speaker",
  "tariffs_page.tariff_module.marketing": "Marketing Module",
  "tariffs_page.tariff_module.meetings": "Meetings Module",
  "tariffs_page.tariff_module.learning": "Learning Module",
  "tariffs_popup.button.to_webinars": "To webinars",
  "mail_inbox_page.recover_password_message.subject": "Restore password",
  "recover_password_page.password_recovered_message": "The password has been successfully changed",
  "sign_in_page.auth_error_message": "The login and password contain errors",
  "sign_in_page.remember_me": "Remember me",
  "sign_in_page.log_in": "Log in",
  "password_recovery_page.success": "Password recovered!",
  "password_recovery_page.message_send": "An e-mail with password recovery instructions was sent to your e-mail address.",
  "event_page.default_name": "New event today",
  "new_test_page.header.done": "Done",
  "event_page.visited": "Visited",
  "webinar_page.nickname": "Nickname",
  "event_edit.edit_schedule.non_repeat": "Do not repeat",
  "event_edit.edit_schedule.every_day": "Every day",
  "event_edit.edit_schedule.every_week": "Every week",
  "event_edit.edit_schedule.every_two_week": "Every two weeks",
  "event_edit.edit_schedule.every_month": "Every month",
  "event_edit.edit_schedule.own_schedule": "My schedule",
  "event_edit.edit_restriction.by_date": "Limit by date",
  "event_edit.edit_restriction.by_quantity": "Limit by number of webinars",
  "event_edit.edit_frequency.every_week": "every week",
  "event_edit.edit_frequency.every_two_week": "every 2 weeks",
  "event_edit.edit_frequency.every_three_week": "every 3 weeks",
  "event_edit.edit_frequency.every_four_week": "every 4 weeks",
  "event_edit.edit_frequency.every_five_week": "every 5 weeks",
  "event_edit.participant_action_dropdown.mark_paid": "Mark as 'paid'",
  "event_registration.popup.access_denied": "Access denied",
  "stream.change_event_date.change_date": "Change date",
  "stream.broadcasting.start_broadcasting": "Start webcasting",
  "stream.broadcasting_popup.microphone": "Microphone",
  "stream.broadcasting_popup.video_quality": "Video quality",
  "stream.broadcasting_popup.error_camera": "Camera not found.",
  "stream.broadcasting_popup.error_microphone": "Microphone not found.",
  "stream.broadcasting_popup.error_camera_and_microphone": "Camera and microphone not found.",
  "stream.page.pause.title": "Pause enabled",
  "stream.page.pause.countdown.default": "The webinar is about to start",
  "stream.page.pause.continue_webinar": "Continue webinar",
  "stream.settings.switch.flash": "Flash",
  "stream.settings.switch.go_on_the_air": "Go on air",
  "stream.settings.switch.language_RU": "Русский язык",
  "stream.settings.switch.language_EN": "English language",
  "stream.settings.switch.font_size_small": "Small font size",
  "stream.settings.switch.font_size_medium": "Medium font size",
  "stream.settings.switch.font_size_large": "Large font size",
  "stream.settings.switch.sound_notifications": "Sound notifications",
  "stream.settings.switch.write_message_to_chat": "Send chat messages",
  "stream.settings.switch.ask_questions": "Ask questions",
  "stream.settings.switch.see_the_list_of_participants": "See participants list",
  "stream.settings.switch.manage_files": "Manage files",
  "stream.approve_go_on_the_air.approve": "Confirm",
  "stream.approve_go_on_the_air.canceling": "Cancel",
  "stream.settings.turn_on_flash": "Turn on",
  "stream.settings.check_on_webrtc": "No way",
  "stream.broadcasting.go_on_the_air": "Go on air",
  "stream.user_actions.open_profile": "Open profile",
  "stream.user_actions.make_admin": "Make an administrator",
  "stream.user_actions.remove_from_admin": "Remove from administrators",
  "stream.user_actions.make_lead": "Make a host",
  "stream.user_actions.resend_link": "Resend the link",
  "stream.user_actions.send_message": "Write a personal message",
  "stream.user_actions.invite_to_stream": "Invite to go on air",
  "stream.user_actions.block": "Block",
  "stream.files.add_file_or_test": "Add file or test",
  "stream.files.create_test": "Create test",
  "stream.files.create_voting": "Create vote",
  "revenue.table_title.paid": "Paid",
  "revenue.table_title.profit": "Revenue in \u20BD.",
  "stream.video_quality.auto": "Auto",
  "stream.video_quality.low": "Low",
  "stream.video_quality.medium": "SD",
  "stream.video_quality.high": "HD",
  "stream.video_quality.hd": "HD",
  "stream.files_actions.open": "Open",
  "stream.files_actions.preview": "Preview",
  "stream.files_actions.unpin_event": "Remove from webinar",
  "stream.files_actions.delete": "Delete",
  "onboarding.label.check_connection": "Now let's check the connection",
  "onboarding.label.nicely_done": "Great, you did it!",
  "onboarding.label.check_equipment": "Check equipment",
  "onboarding.label.check": "Check",
  "onboarding.label.lets_go": "Let's go",
  "onboarding.label.skip": "Skip",
  "onboarding.label.nice_to_meet": "It's nice to meet you",
  "onboarding.label.save": "Save",
  "stream.test_voting.free_answer": "Free answer",
  "stream.test_voting.common_result_access": "to general results",
  "stream.test_voting.individual_result_access": "to individual results",
  "after_event_page.title": "Hold your own online events",
  "after_meeting_page.title": "Meet online!",
  "after_meeting_page.creator_button": "Go to your account",
  "after_meeting_page.guest_button": "Sign up for free",
  "download_file_from_files": "Add from files",
  "download_file_from_pc": "Upload from computer",
  "download_file_board_miro": "Add miro board"
}